lg_adk/__init__.py
lg_adk/agents/__init__.py
lg_adk/agents/base.py
lg_adk/agents/base_agent.py
lg_adk/agents/multi_agent.py
lg_adk/builders/__init__.py
lg_adk/builders/graph_builder.py
lg_adk/cli/__init__.py
lg_adk/cli/commands.py
lg_adk/config/__init__.py
lg_adk/config/settings.py
lg_adk/database/__init__.py
lg_adk/database/database_manager.py
lg_adk/database/db_manager.py
lg_adk/database/managers.py
lg_adk/database/morphik_db.py
lg_adk/database/vector_store.py
lg_adk/eval/__init__.py
lg_adk/eval/dataset.py
lg_adk/eval/evaluator.py
lg_adk/eval/metrics.py
lg_adk/graphs/__init__.py
lg_adk/graphs/chat.py
lg_adk/graphs/chat_graph.py
lg_adk/graphs/multi_agent.py
lg_adk/graphs/rag.py
lg_adk/human/__init__.py
lg_adk/human/human_node.py
lg_adk/human/intervention.py
lg_adk/memory/__init__.py
lg_adk/memory/long_term.py
lg_adk/memory/memory_manager.py
lg_adk/memory/short_term.py
lg_adk/models/__init__.py
lg_adk/models/base.py
lg_adk/models/providers.py
lg_adk/sessions/__init__.py
lg_adk/sessions/session_manager.py
lg_adk/tools/__init__.py
lg_adk/tools/agent_router.py
lg_adk/tools/agent_tools.py
lg_adk/tools/group_chat.py
lg_adk/tools/morphik_retrieval.py
lg_adk/tools/retrieval.py
lg_adk/tools/tool_manager.py
lg_adk/tools/web_search.py
lg_adk/utils/__init__.py
lg_adk/utils/common.py
lg_adk/utils/llm.py
lg_adk/utils/logging.py
lg_adk-1.1.0.dist-info/LICENSE
lg_adk-1.1.0.dist-info/METADATA
lg_adk-1.1.0.dist-info/WHEEL
lg_adk-1.1.0.dist-info/entry_points.txt
lg_adk-1.1.0.dist-info/RECORD
