Metadata-Version: 2.3
Name: lg-adk
Version: 1.1.0
Summary: Agent Development Kit for LangGraph - A framework for building LangGraph-based agent systems
License: MIT
Author: Your Name
Author-email: you@example.com
Requires-Python: >=3.11,<4.0
Classifier: License :: OSI Approved :: MIT License
Classifier: Programming Language :: Python :: 3
Classifier: Programming Language :: Python :: 3.11
Classifier: Programming Language :: Python :: 3.12
Classifier: Programming Language :: Python :: 3.13
Provides-Extra: morphik
Requires-Dist: chromadb (>=0.4.22,<0.5.0)
Requires-Dist: click (>=8.0.0,<9.0.0)
Requires-Dist: faiss-cpu (>=1.11.0,<2.0.0)
Requires-Dist: google-generativeai (>=0.3.1,<0.4.0)
Requires-Dist: langchain (>=0.3.24,<0.4.0)
Requires-Dist: langchain-community (>=0.3.22,<0.4.0)
Requires-Dist: langchain-core (>=0.3.55,<0.4.0)
Requires-Dist: langchain-openai (>=0.3.16,<0.4.0)
Requires-Dist: langgraph (>=0.3.32,<0.4.0)
Requires-Dist: langsmith (>=0.0.83)
Requires-Dist: litellm (>=1.13.0,<2.0.0)
Requires-Dist: loguru (>=0.7.3,<0.8.0)
Requires-Dist: morphik (>=0.1.0) ; extra == "morphik"
Requires-Dist: ollama (>=0.1.6,<0.2.0)
Requires-Dist: pydantic (>=2.5.3,<3.0.0)
Requires-Dist: pydantic-settings (>=2.9.1,<3.0.0)
Requires-Dist: rich (>=13.7.0,<14.0.0)
Requires-Dist: sentence-transformers (>=2.2.2,<3.0.0)
Requires-Dist: tiktoken (>=0.7.0,<0.8.0)
